atooms/__init__.py
atooms/landscape/__init__.py
atooms/landscape/core.py
atooms/landscape/factory.py
atooms/landscape/helpers.py
atooms/landscape/methods/__init__.py
atooms/landscape/methods/ef.py
atooms/landscape/methods/fire.py
atooms/landscape/methods/ridge.py
atooms/landscape/methods/sd.py
atooms/landscape/surfaces/__init__.py
atooms/landscape/surfaces/force_norm_square.py
atooms/landscape/surfaces/muller_brown.py
atooms/landscape/surfaces/multi_saddle.py
atooms/landscape/surfaces/potential_energy.py
atooms/landscape/surfaces/rosenbrock.py
atooms_landscape-2.0.1.dist-info/LICENSE
atooms_landscape-2.0.1.dist-info/METADATA
atooms_landscape-2.0.1.dist-info/WHEEL
atooms_landscape-2.0.1.dist-info/top_level.txt
atooms_landscape-2.0.1.dist-info/RECORD
