Metadata-Version: 2.1
Name: atooms-landscape
Version: 2.0.1
Summary: Energy landscape analysis tools built with atooms
Home-page: https://framagit.org/atooms/landscape
Author: Daniele Coslovich
Author-email: daniele.coslovich@umontpellier.fr
License: GPLv3
Platform: UNKNOWN
Classifier: License :: OSI Approved :: GNU General Public License v3 (GPLv3)
Classifier: Programming Language :: Python :: 3
Classifier: Programming Language :: Python :: 3.6
License-File: LICENSE
Requires-Dist: atooms (>=3.20.1)
Requires-Dist: f2py-jit (>=0.5.0)
Requires-Dist: scipy
